README.md
setup.cfg
setup.py
celebrity_birth_test.egg-info/PKG-INFO
celebrity_birth_test.egg-info/SOURCES.txt
celebrity_birth_test.egg-info/dependency_links.txt
celebrity_birth_test.egg-info/requires.txt
celebrity_birth_test.egg-info/top_level.txt
project/Date.py
project/Scraper.py
project/__init__.py
project/__main__.py
project/celebrities_births.py