Metadata-Version: 1.0
Name: celebrity-birth-test
Version: 0.0.1
Summary: Package that will help find celeb birthdays
Home-page: https://github.com/MilanSajiv/Celebrities-Births/tree/main/Celebrities_Births/project
Author: Milan Sajiv
Author-email: milansajiv@hotmail.co.uk
License: MIT
Platform: UNKNOWN
